kindly/__init__.py
kindly/__main__.py
kindly/_aliases_provider.py
kindly/_cli.py
kindly/_pathutils.py
kindly/api.py
kindly/py.typed
kindly-0.3.0.dist-info/LICENSE
kindly-0.3.0.dist-info/METADATA
kindly-0.3.0.dist-info/WHEEL
kindly-0.3.0.dist-info/entry_points.txt
kindly-0.3.0.dist-info/RECORD
